CHANGES.txt
LICENSE.txt
README.txt
bootstrap.py
buildout.cfg
setup.py
testing.cfg
src/s01/__init__.py
src/s01.client.egg-info/PKG-INFO
src/s01.client.egg-info/SOURCES.txt
src/s01.client.egg-info/dependency_links.txt
src/s01.client.egg-info/namespace_packages.txt
src/s01.client.egg-info/not-zip-safe
src/s01.client.egg-info/requires.txt
src/s01.client.egg-info/top_level.txt
src/s01/client/README.txt
src/s01/client/__init__.py
src/s01/client/proxy.py
src/s01/client/tests.py